gpmap/__init__.py
gpmap/aligner.py
gpmap/datasets.py
gpmap/genotypes.py
gpmap/gp.py
gpmap/graph.py
gpmap/inference.py
gpmap/kernel.py
gpmap/likelihood.py
gpmap/linalg.py
gpmap/linop.py
gpmap/matrix.py
gpmap/randwalk.py
gpmap/seq.py
gpmap/settings.py
gpmap/space.py
gpmap/summary.py
gpmap/utils.py
gpmap/bin/__init__.py
gpmap/bin/calc_tpt.py
gpmap/bin/calc_visualization.py
gpmap/bin/evaluate_split_fits.py
gpmap/bin/filter_genotypes.py
gpmap/bin/fit_seqdeft.py
gpmap/bin/plot_relaxation_times.py
gpmap/bin/plot_visualization.py
gpmap/bin/split_data.py
gpmap/bin/vc_regression.py
gpmap/datasets/data/5ss.pq
gpmap/datasets/data/Flynn2013.csv
gpmap/datasets/data/Weinreich2006.beta_lactamase.csv
gpmap/datasets/data/dmsc.pq
gpmap/datasets/data/f1u.pq
gpmap/datasets/data/gb1.pq
gpmap/datasets/data/pard.pq
gpmap/datasets/data/serine.pq
gpmap/datasets/data/shine_dalgarno.pq
gpmap/datasets/data/smn1.pq
gpmap/datasets/data/test.pq
gpmap/datasets/data/trna.pq
gpmap/datasets/landscapes/5ss.pq
gpmap/datasets/landscapes/dmsc.pq
gpmap/datasets/landscapes/f1u.pq
gpmap/datasets/landscapes/gb1.pq
gpmap/datasets/landscapes/pard.pq
gpmap/datasets/landscapes/serine.pq
gpmap/datasets/landscapes/shine_dalgarno.pq
gpmap/datasets/landscapes/smn1.pq
gpmap/datasets/landscapes/test.pq
gpmap/datasets/landscapes/trna.pq
gpmap/datasets/raw/5ss.pq
gpmap/datasets/raw/gb1.pq
gpmap/datasets/raw/pard.pq
gpmap/datasets/visualizations/5ss.edges.npz
gpmap/datasets/visualizations/5ss.nodes.pq
gpmap/datasets/visualizations/5ss.relaxation_times.pq
gpmap/datasets/visualizations/f1u.edges.npz
gpmap/datasets/visualizations/f1u.nodes.pq
gpmap/datasets/visualizations/f1u.relaxation_times.pq
gpmap/datasets/visualizations/gb1.decay_rates.csv
gpmap/datasets/visualizations/gb1.edges.npz
gpmap/datasets/visualizations/gb1.nodes.pq
gpmap/datasets/visualizations/gb1.relaxation_times.pq
gpmap/datasets/visualizations/serine.edges.npz
gpmap/datasets/visualizations/serine.nodes.pq
gpmap_tools-0.3.3.dist-info/LICENSE
gpmap_tools-0.3.3.dist-info/METADATA
gpmap_tools-0.3.3.dist-info/WHEEL
gpmap_tools-0.3.3.dist-info/entry_points.txt
gpmap_tools-0.3.3.dist-info/top_level.txt
gpmap_tools-0.3.3.dist-info/RECORD
