Metadata-Version: 2.1
Name: gpmap_tools
Version: 0.3.3
Summary: Tools for inference and visualization of complex genotype-phenotype maps
Author-email: Carlos Martí-Gómez <martigo@cshl.edu>
License: MIT
Project-URL: Documentation, https://gpmap-tools.readthedocs.io
Project-URL: Repository, https://github.com/cmarti/gpmap-tools.git
Keywords: genotype-phenotype maps,fitness landscape,exact gaussian process regression
Classifier: Programming Language :: Python :: 3
Classifier: Intended Audience :: Science/Research
Classifier: License :: OSI Approved :: MIT License
Classifier: Operating System :: OS Independent
Requires-Python: >=3.8
License-File: LICENSE
Requires-Dist: biopython
Requires-Dist: matplotlib
Requires-Dist: tqdm
Requires-Dist: numpy
Requires-Dist: scipy
Requires-Dist: pandas
Requires-Dist: pyarrow
Requires-Dist: networkx
Requires-Dist: datashader >=0.13.0
Requires-Dist: holoviews >=1.15.0
Requires-Dist: plotly ==5.18.0
